[
  {
    "@id": "urn:ucode:_00001C0000000000000100000317A583",
    "@type": "odpt:RailwayFare",
    "dc:date": "2025-06-30T15:00:00+09:00",
    "@context": "http://vocab.odpt.org/context_odpt.jsonld",
    "dct:issued": "2023-03-18",
    "owl:sameAs": "odpt.RailwayFare:Tokyu.Ikegami.Yukigayaotsuka.Tokyu.DenEnToshi.Aobadai",
    "odpt:operator": "odpt.Operator:Tokyu",
    "odpt:toStation": "odpt.Station:Tokyu.DenEnToshi.Aobadai",
    "odpt:icCardFare": 309,
    "odpt:ticketFare": 310,
    "odpt:fromStation": "odpt.Station:Tokyu.Ikegami.Yukigayaotsuka",
    "odpt:childIcCardFare": 154,
    "odpt:childTicketFare": 160
  },
  {
    "@id": "urn:ucode:_00001C0000000000000100000317A584",
    "@type": "odpt:RailwayFare",
    "dc:date": "2025-06-30T15:00:00+09:00",
    "@context": "http://vocab.odpt.org/context_odpt.jsonld",
    "dct:issued": "2023-03-18",
    "owl:sameAs": "odpt.RailwayFare:Tokyu.Ikegami.Yukigayaotsuka.Tokyu.DenEnToshi.Azamino",
    "odpt:operator": "odpt.Operator:Tokyu",
    "odpt:toStation": "odpt.Station:Tokyu.DenEnToshi.Azamino",
    "odpt:icCardFare": 288,
    "odpt:ticketFare": 290,
    "odpt:fromStation": "odpt.Station:Tokyu.Ikegami.Yukigayaotsuka",
    "odpt:childIcCardFare": 144,
    "odpt:childTicketFare": 150
  },
  {
    "@id": "urn:ucode:_00001C0000000000000100000317A585",
    "@type": "odpt:RailwayFare",
    "dc:date": "2025-06-30T15:00:00+09:00",
    "@context": "http://vocab.odpt.org/context_odpt.jsonld",
    "dct:issued": "2023-03-18",
    "owl:sameAs": "odpt.RailwayFare:Tokyu.Ikegami.Yukigayaotsuka.Tokyu.DenEnToshi.ChuoRinkan",
    "odpt:operator": "odpt.Operator:Tokyu",
    "odpt:toStation": "odpt.Station:Tokyu.DenEnToshi.ChuoRinkan",
    "odpt:icCardFare": 381,
    "odpt:ticketFare": 390,
    "odpt:fromStation": "odpt.Station:Tokyu.Ikegami.Yukigayaotsuka",
    "odpt:childIcCardFare": 190,
    "odpt:childTicketFare": 200
  },
  {
    "@id": "urn:ucode:_00001C0000000000000100000317A586",
    "@type": "odpt:RailwayFare",
    "dc:date": "2025-06-30T15:00:00+09:00",
    "@context": "http://vocab.odpt.org/context_odpt.jsonld",
    "dct:issued": "2023-03-18",
    "owl:sameAs": "odpt.RailwayFare:Tokyu.Ikegami.Yukigayaotsuka.Tokyu.DenEnToshi.Eda",
    "odpt:operator": "odpt.Operator:Tokyu",
    "odpt:toStation": "odpt.Station:Tokyu.DenEnToshi.Eda",
    "odpt:icCardFare": 288,
    "odpt:ticketFare": 290,
    "odpt:fromStation": "odpt.Station:Tokyu.Ikegami.Yukigayaotsuka",
    "odpt:childIcCardFare": 144,
    "odpt:childTicketFare": 150
  },
  {
    "@id": "urn:ucode:_00001C0000000000000100000317A587",
    "@type": "odpt:RailwayFare",
    "dc:date": "2025-06-30T15:00:00+09:00",
    "@context": "http://vocab.odpt.org/context_odpt.jsonld",
    "dct:issued": "2023-03-18",
    "owl:sameAs": "odpt.RailwayFare:Tokyu.Ikegami.Yukigayaotsuka.Tokyu.DenEnToshi.Fujigaoka",
    "odpt:operator": "odpt.Operator:Tokyu",
    "odpt:toStation": "odpt.Station:Tokyu.DenEnToshi.Fujigaoka",
    "odpt:icCardFare": 309,
    "odpt:ticketFare": 310,
    "odpt:fromStation": "odpt.Station:Tokyu.Ikegami.Yukigayaotsuka",
    "odpt:childIcCardFare": 154,
    "odpt:childTicketFare": 160
  },
  {
    "@id": "urn:ucode:_00001C0000000000000100000317A588",
    "@type": "odpt:RailwayFare",
    "dc:date": "2025-06-30T15:00:00+09:00",
    "@context": "http://vocab.odpt.org/context_odpt.jsonld",
    "dct:issued": "2023-03-18",
    "owl:sameAs": "odpt.RailwayFare:Tokyu.Ikegami.Yukigayaotsuka.Tokyu.DenEnToshi.FutakoShinchi",
    "odpt:operator": "odpt.Operator:Tokyu",
    "odpt:toStation": "odpt.Station:Tokyu.DenEnToshi.FutakoShinchi",
    "odpt:icCardFare": 227,
    "odpt:ticketFare": 230,
    "odpt:fromStation": "odpt.Station:Tokyu.Ikegami.Yukigayaotsuka",
    "odpt:childIcCardFare": 113,
    "odpt:childTicketFare": 120
  },
  {
    "@id": "urn:ucode:_00001C0000000000000100000317A589",
    "@type": "odpt:RailwayFare",
    "dc:date": "2025-06-30T15:00:00+09:00",
    "@context": "http://vocab.odpt.org/context_odpt.jsonld",
    "dct:issued": "2023-03-18",
    "owl:sameAs": "odpt.RailwayFare:Tokyu.Ikegami.Yukigayaotsuka.Tokyu.DenEnToshi.FutakoTamagawa",
    "odpt:operator": "odpt.Operator:Tokyu",
    "odpt:toStation": "odpt.Station:Tokyu.DenEnToshi.FutakoTamagawa",
    "odpt:icCardFare": 227,
    "odpt:ticketFare": 230,
    "odpt:fromStation": "odpt.Station:Tokyu.Ikegami.Yukigayaotsuka",
    "odpt:childIcCardFare": 113,
    "odpt:childTicketFare": 120
  },
  {
    "@id": "urn:ucode:_00001C0000000000000100000317A58A",
    "@type": "odpt:RailwayFare",
    "dc:date": "2025-06-30T15:00:00+09:00",
    "@context": "http://vocab.odpt.org/context_odpt.jsonld",
    "dct:issued": "2023-03-18",
    "owl:sameAs": "odpt.RailwayFare:Tokyu.Ikegami.Yukigayaotsuka.Tokyu.DenEnToshi.Ichigao",
    "odpt:operator": "odpt.Operator:Tokyu",
    "odpt:toStation": "odpt.Station:Tokyu.DenEnToshi.Ichigao",
    "odpt:icCardFare": 309,
    "odpt:ticketFare": 310,
    "odpt:fromStation": "odpt.Station:Tokyu.Ikegami.Yukigayaotsuka",
    "odpt:childIcCardFare": 154,
    "odpt:childTicketFare": 160
  },
  {
    "@id": "urn:ucode:_00001C0000000000000100000317A58B",
    "@type": "odpt:RailwayFare",
    "dc:date": "2025-06-30T15:00:00+09:00",
    "@context": "http://vocab.odpt.org/context_odpt.jsonld",
    "dct:issued": "2023-03-18",
    "owl:sameAs": "odpt.RailwayFare:Tokyu.Ikegami.Yukigayaotsuka.Tokyu.DenEnToshi.Ikejiriohashi",
    "odpt:operator": "odpt.Operator:Tokyu",
    "odpt:toStation": "odpt.Station:Tokyu.DenEnToshi.Ikejiriohashi",
    "odpt:icCardFare": 250,
    "odpt:ticketFare": 250,
    "odpt:fromStation": "odpt.Station:Tokyu.Ikegami.Yukigayaotsuka",
    "odpt:childIcCardFare": 125,
    "odpt:childTicketFare": 130
  },
  {
    "@id": "urn:ucode:_00001C0000000000000100000317A58C",
    "@type": "odpt:RailwayFare",
    "dc:date": "2025-06-30T15:00:00+09:00",
    "@context": "http://vocab.odpt.org/context_odpt.jsonld",
    "dct:issued": "2023-03-18",
    "owl:sameAs": "odpt.RailwayFare:Tokyu.Ikegami.Yukigayaotsuka.Tokyu.DenEnToshi.Kajigaya",
    "odpt:operator": "odpt.Operator:Tokyu",
    "odpt:toStation": "odpt.Station:Tokyu.DenEnToshi.Kajigaya",
    "odpt:icCardFare": 250,
    "odpt:ticketFare": 250,
    "odpt:fromStation": "odpt.Station:Tokyu.Ikegami.Yukigayaotsuka",
    "odpt:childIcCardFare": 125,
    "odpt:childTicketFare": 130
  },
  {
    "@id": "urn:ucode:_00001C0000000000000100000317A58D",
    "@type": "odpt:RailwayFare",
    "dc:date": "2025-06-30T15:00:00+09:00",
    "@context": "http://vocab.odpt.org/context_odpt.jsonld",
    "dct:issued": "2023-03-18",
    "owl:sameAs": "odpt.RailwayFare:Tokyu.Ikegami.Yukigayaotsuka.Tokyu.DenEnToshi.KomazawaDaigaku",
    "odpt:operator": "odpt.Operator:Tokyu",
    "odpt:toStation": "odpt.Station:Tokyu.DenEnToshi.KomazawaDaigaku",
    "odpt:icCardFare": 250,
    "odpt:ticketFare": 250,
    "odpt:fromStation": "odpt.Station:Tokyu.Ikegami.Yukigayaotsuka",
    "odpt:childIcCardFare": 125,
    "odpt:childTicketFare": 130
  },
  {
    "@id": "urn:ucode:_00001C0000000000000100000317A58E",
    "@type": "odpt:RailwayFare",
    "dc:date": "2025-06-30T15:00:00+09:00",
    "@context": "http://vocab.odpt.org/context_odpt.jsonld",
    "dct:issued": "2023-03-18",
    "owl:sameAs": "odpt.RailwayFare:Tokyu.Ikegami.Yukigayaotsuka.Tokyu.DenEnToshi.MinamiMachidaGrandberryPark",
    "odpt:operator": "odpt.Operator:Tokyu",
    "odpt:toStation": "odpt.Station:Tokyu.DenEnToshi.MinamiMachidaGrandberryPark",
    "odpt:icCardFare": 347,
    "odpt:ticketFare": 350,
    "odpt:fromStation": "odpt.Station:Tokyu.Ikegami.Yukigayaotsuka",
    "odpt:childIcCardFare": 173,
    "odpt:childTicketFare": 180
  },
  {
    "@id": "urn:ucode:_00001C0000000000000100000317A58F",
    "@type": "odpt:RailwayFare",
    "dc:date": "2025-06-30T15:00:00+09:00",
    "@context": "http://vocab.odpt.org/context_odpt.jsonld",
    "dct:issued": "2023-03-18",
    "owl:sameAs": "odpt.RailwayFare:Tokyu.Ikegami.Yukigayaotsuka.Tokyu.DenEnToshi.Miyamaedaira",
    "odpt:operator": "odpt.Operator:Tokyu",
    "odpt:toStation": "odpt.Station:Tokyu.DenEnToshi.Miyamaedaira",
    "odpt:icCardFare": 250,
    "odpt:ticketFare": 250,
    "odpt:fromStation": "odpt.Station:Tokyu.Ikegami.Yukigayaotsuka",
    "odpt:childIcCardFare": 125,
    "odpt:childTicketFare": 130
  },
  {
    "@id": "urn:ucode:_00001C0000000000000100000317A590",
    "@type": "odpt:RailwayFare",
    "dc:date": "2025-06-30T15:00:00+09:00",
    "@context": "http://vocab.odpt.org/context_odpt.jsonld",
    "dct:issued": "2023-03-18",
    "owl:sameAs": "odpt.RailwayFare:Tokyu.Ikegami.Yukigayaotsuka.Tokyu.DenEnToshi.Miyazakidai",
    "odpt:operator": "odpt.Operator:Tokyu",
    "odpt:toStation": "odpt.Station:Tokyu.DenEnToshi.Miyazakidai",
    "odpt:icCardFare": 250,
    "odpt:ticketFare": 250,
    "odpt:fromStation": "odpt.Station:Tokyu.Ikegami.Yukigayaotsuka",
    "odpt:childIcCardFare": 125,
    "odpt:childTicketFare": 130
  },
  {
    "@id": "urn:ucode:_00001C0000000000000100000317A591",
    "@type": "odpt:RailwayFare",
    "dc:date": "2025-06-30T15:00:00+09:00",
    "@context": "http://vocab.odpt.org/context_odpt.jsonld",
    "dct:issued": "2023-03-18",
    "owl:sameAs": "odpt.RailwayFare:Tokyu.Ikegami.Yukigayaotsuka.Tokyu.DenEnToshi.Mizonokuchi",
    "odpt:operator": "odpt.Operator:Tokyu",
    "odpt:toStation": "odpt.Station:Tokyu.DenEnToshi.Mizonokuchi",
    "odpt:icCardFare": 250,
    "odpt:ticketFare": 250,
    "odpt:fromStation": "odpt.Station:Tokyu.Ikegami.Yukigayaotsuka",
    "odpt:childIcCardFare": 125,
    "odpt:childTicketFare": 130
  },
  {
    "@id": "urn:ucode:_00001C0000000000000100000317A592",
    "@type": "odpt:RailwayFare",
    "dc:date": "2025-06-30T15:00:00+09:00",
    "@context": "http://vocab.odpt.org/context_odpt.jsonld",
    "dct:issued": "2023-03-18",
    "owl:sameAs": "odpt.RailwayFare:Tokyu.Ikegami.Yukigayaotsuka.Tokyu.DenEnToshi.Nagatsuta",
    "odpt:operator": "odpt.Operator:Tokyu",
    "odpt:toStation": "odpt.Station:Tokyu.DenEnToshi.Nagatsuta",
    "odpt:icCardFare": 347,
    "odpt:ticketFare": 350,
    "odpt:fromStation": "odpt.Station:Tokyu.Ikegami.Yukigayaotsuka",
    "odpt:childIcCardFare": 173,
    "odpt:childTicketFare": 180
  },
  {
    "@id": "urn:ucode:_00001C0000000000000100000317A593",
    "@type": "odpt:RailwayFare",
    "dc:date": "2025-06-30T15:00:00+09:00",
    "@context": "http://vocab.odpt.org/context_odpt.jsonld",
    "dct:issued": "2023-03-18",
    "owl:sameAs": "odpt.RailwayFare:Tokyu.Ikegami.Yukigayaotsuka.Tokyu.DenEnToshi.Saginuma",
    "odpt:operator": "odpt.Operator:Tokyu",
    "odpt:toStation": "odpt.Station:Tokyu.DenEnToshi.Saginuma",
    "odpt:icCardFare": 288,
    "odpt:ticketFare": 290,
    "odpt:fromStation": "odpt.Station:Tokyu.Ikegami.Yukigayaotsuka",
    "odpt:childIcCardFare": 144,
    "odpt:childTicketFare": 150
  },
  {
    "@id": "urn:ucode:_00001C0000000000000100000317A594",
    "@type": "odpt:RailwayFare",
    "dc:date": "2025-06-30T15:00:00+09:00",
    "@context": "http://vocab.odpt.org/context_odpt.jsonld",
    "dct:issued": "2023-03-18",
    "owl:sameAs": "odpt.RailwayFare:Tokyu.Ikegami.Yukigayaotsuka.Tokyu.DenEnToshi.SakuraShimmachi",
    "odpt:operator": "odpt.Operator:Tokyu",
    "odpt:toStation": "odpt.Station:Tokyu.DenEnToshi.SakuraShimmachi",
    "odpt:icCardFare": 250,
    "odpt:ticketFare": 250,
    "odpt:fromStation": "odpt.Station:Tokyu.Ikegami.Yukigayaotsuka",
    "odpt:childIcCardFare": 125,
    "odpt:childTicketFare": 130
  },
  {
    "@id": "urn:ucode:_00001C0000000000000100000317A595",
    "@type": "odpt:RailwayFare",
    "dc:date": "2025-06-30T15:00:00+09:00",
    "@context": "http://vocab.odpt.org/context_odpt.jsonld",
    "dct:issued": "2023-03-18",
    "owl:sameAs": "odpt.RailwayFare:Tokyu.Ikegami.Yukigayaotsuka.Tokyu.DenEnToshi.SangenJaya",
    "odpt:operator": "odpt.Operator:Tokyu",
    "odpt:toStation": "odpt.Station:Tokyu.DenEnToshi.SangenJaya",
    "odpt:icCardFare": 288,
    "odpt:ticketFare": 290,
    "odpt:fromStation": "odpt.Station:Tokyu.Ikegami.Yukigayaotsuka",
    "odpt:childIcCardFare": 144,
    "odpt:childTicketFare": 150
  },
  {
    "@id": "urn:ucode:_00001C0000000000000100000317A596",
    "@type": "odpt:RailwayFare",
    "dc:date": "2025-06-30T15:00:00+09:00",
    "@context": "http://vocab.odpt.org/context_odpt.jsonld",
    "dct:issued": "2023-03-18",
    "owl:sameAs": "odpt.RailwayFare:Tokyu.Ikegami.Yukigayaotsuka.Tokyu.DenEnToshi.Shibuya",
    "odpt:operator": "odpt.Operator:Tokyu",
    "odpt:toStation": "odpt.Station:Tokyu.DenEnToshi.Shibuya",
    "odpt:icCardFare": 250,
    "odpt:ticketFare": 250,
    "odpt:fromStation": "odpt.Station:Tokyu.Ikegami.Yukigayaotsuka",
    "odpt:childIcCardFare": 125,
    "odpt:childTicketFare": 130
  },
  {
    "@id": "urn:ucode:_00001C0000000000000100000317A597",
    "@type": "odpt:RailwayFare",
    "dc:date": "2025-06-30T15:00:00+09:00",
    "@context": "http://vocab.odpt.org/context_odpt.jsonld",
    "dct:issued": "2023-03-18",
    "owl:sameAs": "odpt.RailwayFare:Tokyu.Ikegami.Yukigayaotsuka.Tokyu.DenEnToshi.Suzukakedai",
    "odpt:operator": "odpt.Operator:Tokyu",
    "odpt:toStation": "odpt.Station:Tokyu.DenEnToshi.Suzukakedai",
    "odpt:icCardFare": 347,
    "odpt:ticketFare": 350,
    "odpt:fromStation": "odpt.Station:Tokyu.Ikegami.Yukigayaotsuka",
    "odpt:childIcCardFare": 173,
    "odpt:childTicketFare": 180
  },
  {
    "@id": "urn:ucode:_00001C0000000000000100000317A598",
    "@type": "odpt:RailwayFare",
    "dc:date": "2025-06-30T15:00:00+09:00",
    "@context": "http://vocab.odpt.org/context_odpt.jsonld",
    "dct:issued": "2023-03-18",
    "owl:sameAs": "odpt.RailwayFare:Tokyu.Ikegami.Yukigayaotsuka.Tokyu.DenEnToshi.Takatsu",
    "odpt:operator": "odpt.Operator:Tokyu",
    "odpt:toStation": "odpt.Station:Tokyu.DenEnToshi.Takatsu",
    "odpt:icCardFare": 227,
    "odpt:ticketFare": 230,
    "odpt:fromStation": "odpt.Station:Tokyu.Ikegami.Yukigayaotsuka",
    "odpt:childIcCardFare": 113,
    "odpt:childTicketFare": 120
  },
  {
    "@id": "urn:ucode:_00001C0000000000000100000317A599",
    "@type": "odpt:RailwayFare",
    "dc:date": "2025-06-30T15:00:00+09:00",
    "@context": "http://vocab.odpt.org/context_odpt.jsonld",
    "dct:issued": "2023-03-18",
    "owl:sameAs": "odpt.RailwayFare:Tokyu.Ikegami.Yukigayaotsuka.Tokyu.DenEnToshi.TamaPlaza",
    "odpt:operator": "odpt.Operator:Tokyu",
    "odpt:toStation": "odpt.Station:Tokyu.DenEnToshi.TamaPlaza",
    "odpt:icCardFare": 288,
    "odpt:ticketFare": 290,
    "odpt:fromStation": "odpt.Station:Tokyu.Ikegami.Yukigayaotsuka",
    "odpt:childIcCardFare": 144,
    "odpt:childTicketFare": 150
  },
  {
    "@id": "urn:ucode:_00001C0000000000000100000317A59A",
    "@type": "odpt:RailwayFare",
    "dc:date": "2025-06-30T15:00:00+09:00",
    "@context": "http://vocab.odpt.org/context_odpt.jsonld",
    "dct:issued": "2023-03-18",
    "owl:sameAs": "odpt.RailwayFare:Tokyu.Ikegami.Yukigayaotsuka.Tokyu.DenEnToshi.Tana",
    "odpt:operator": "odpt.Operator:Tokyu",
    "odpt:toStation": "odpt.Station:Tokyu.DenEnToshi.Tana",
    "odpt:icCardFare": 309,
    "odpt:ticketFare": 310,
    "odpt:fromStation": "odpt.Station:Tokyu.Ikegami.Yukigayaotsuka",
    "odpt:childIcCardFare": 154,
    "odpt:childTicketFare": 160
  },
  {
    "@id": "urn:ucode:_00001C0000000000000100000317A59B",
    "@type": "odpt:RailwayFare",
    "dc:date": "2025-06-30T15:00:00+09:00",
    "@context": "http://vocab.odpt.org/context_odpt.jsonld",
    "dct:issued": "2023-03-18",
    "owl:sameAs": "odpt.RailwayFare:Tokyu.Ikegami.Yukigayaotsuka.Tokyu.DenEnToshi.Tsukimino",
    "odpt:operator": "odpt.Operator:Tokyu",
    "odpt:toStation": "odpt.Station:Tokyu.DenEnToshi.Tsukimino",
    "odpt:icCardFare": 381,
    "odpt:ticketFare": 390,
    "odpt:fromStation": "odpt.Station:Tokyu.Ikegami.Yukigayaotsuka",
    "odpt:childIcCardFare": 190,
    "odpt:childTicketFare": 200
  },
  {
    "@id": "urn:ucode:_00001C0000000000000100000317A59C",
    "@type": "odpt:RailwayFare",
    "dc:date": "2025-06-30T15:00:00+09:00",
    "@context": "http://vocab.odpt.org/context_odpt.jsonld",
    "dct:issued": "2023-03-18",
    "owl:sameAs": "odpt.RailwayFare:Tokyu.Ikegami.Yukigayaotsuka.Tokyu.DenEnToshi.Tsukushino",
    "odpt:operator": "odpt.Operator:Tokyu",
    "odpt:toStation": "odpt.Station:Tokyu.DenEnToshi.Tsukushino",
    "odpt:icCardFare": 347,
    "odpt:ticketFare": 350,
    "odpt:fromStation": "odpt.Station:Tokyu.Ikegami.Yukigayaotsuka",
    "odpt:childIcCardFare": 173,
    "odpt:childTicketFare": 180
  },
  {
    "@id": "urn:ucode:_00001C0000000000000100000317A59D",
    "@type": "odpt:RailwayFare",
    "dc:date": "2025-06-30T15:00:00+09:00",
    "@context": "http://vocab.odpt.org/context_odpt.jsonld",
    "dct:issued": "2023-03-18",
    "owl:sameAs": "odpt.RailwayFare:Tokyu.Ikegami.Yukigayaotsuka.Tokyu.DenEnToshi.Yoga",
    "odpt:operator": "odpt.Operator:Tokyu",
    "odpt:toStation": "odpt.Station:Tokyu.DenEnToshi.Yoga",
    "odpt:icCardFare": 250,
    "odpt:ticketFare": 250,
    "odpt:fromStation": "odpt.Station:Tokyu.Ikegami.Yukigayaotsuka",
    "odpt:childIcCardFare": 125,
    "odpt:childTicketFare": 130
  },
  {
    "@id": "urn:ucode:_00001C0000000000000100000317A59E",
    "@type": "odpt:RailwayFare",
    "dc:date": "2025-06-30T15:00:00+09:00",
    "@context": "http://vocab.odpt.org/context_odpt.jsonld",
    "dct:issued": "2023-03-18",
    "owl:sameAs": "odpt.RailwayFare:Tokyu.Ikegami.Yukigayaotsuka.Tokyu.Ikegami.Chidoricho",
    "odpt:operator": "odpt.Operator:Tokyu",
    "odpt:toStation": "odpt.Station:Tokyu.Ikegami.Chidoricho",
    "odpt:icCardFare": 140,
    "odpt:ticketFare": 140,
    "odpt:fromStation": "odpt.Station:Tokyu.Ikegami.Yukigayaotsuka",
    "odpt:childIcCardFare": 70,
    "odpt:childTicketFare": 70
  },
  {
    "@id": "urn:ucode:_00001C0000000000000100000317A59F",
    "@type": "odpt:RailwayFare",
    "dc:date": "2025-06-30T15:00:00+09:00",
    "@context": "http://vocab.odpt.org/context_odpt.jsonld",
    "dct:issued": "2023-03-18",
    "owl:sameAs": "odpt.RailwayFare:Tokyu.Ikegami.Yukigayaotsuka.Tokyu.Ikegami.EbaraNakanobu",
    "odpt:operator": "odpt.Operator:Tokyu",
    "odpt:toStation": "odpt.Station:Tokyu.Ikegami.EbaraNakanobu",
    "odpt:icCardFare": 180,
    "odpt:ticketFare": 180,
    "odpt:fromStation": "odpt.Station:Tokyu.Ikegami.Yukigayaotsuka",
    "odpt:childIcCardFare": 90,
    "odpt:childTicketFare": 90
  },
  {
    "@id": "urn:ucode:_00001C0000000000000100000317A5A0",
    "@type": "odpt:RailwayFare",
    "dc:date": "2025-06-30T15:00:00+09:00",
    "@context": "http://vocab.odpt.org/context_odpt.jsonld",
    "dct:issued": "2023-03-18",
    "owl:sameAs": "odpt.RailwayFare:Tokyu.Ikegami.Yukigayaotsuka.Tokyu.Ikegami.Gotanda",
    "odpt:operator": "odpt.Operator:Tokyu",
    "odpt:toStation": "odpt.Station:Tokyu.Ikegami.Gotanda",
    "odpt:icCardFare": 180,
    "odpt:ticketFare": 180,
    "odpt:fromStation": "odpt.Station:Tokyu.Ikegami.Yukigayaotsuka",
    "odpt:childIcCardFare": 90,
    "odpt:childTicketFare": 90
  },
  {
    "@id": "urn:ucode:_00001C0000000000000100000317A5A1",
    "@type": "odpt:RailwayFare",
    "dc:date": "2025-06-30T15:00:00+09:00",
    "@context": "http://vocab.odpt.org/context_odpt.jsonld",
    "dct:issued": "2023-03-18",
    "owl:sameAs": "odpt.RailwayFare:Tokyu.Ikegami.Yukigayaotsuka.Tokyu.Ikegami.Hasunuma",
    "odpt:operator": "odpt.Operator:Tokyu",
    "odpt:toStation": "odpt.Station:Tokyu.Ikegami.Hasunuma",
    "odpt:icCardFare": 180,
    "odpt:ticketFare": 180,
    "odpt:fromStation": "odpt.Station:Tokyu.Ikegami.Yukigayaotsuka",
    "odpt:childIcCardFare": 90,
    "odpt:childTicketFare": 90
  },
  {
    "@id": "urn:ucode:_00001C0000000000000100000317A5A2",
    "@type": "odpt:RailwayFare",
    "dc:date": "2025-06-30T15:00:00+09:00",
    "@context": "http://vocab.odpt.org/context_odpt.jsonld",
    "dct:issued": "2023-03-18",
    "owl:sameAs": "odpt.RailwayFare:Tokyu.Ikegami.Yukigayaotsuka.Tokyu.Ikegami.Hatanodai",
    "odpt:operator": "odpt.Operator:Tokyu",
    "odpt:toStation": "odpt.Station:Tokyu.Ikegami.Hatanodai",
    "odpt:icCardFare": 140,
    "odpt:ticketFare": 140,
    "odpt:fromStation": "odpt.Station:Tokyu.Ikegami.Yukigayaotsuka",
    "odpt:childIcCardFare": 70,
    "odpt:childTicketFare": 70
  },
  {
    "@id": "urn:ucode:_00001C0000000000000100000317A5A3",
    "@type": "odpt:RailwayFare",
    "dc:date": "2025-06-30T15:00:00+09:00",
    "@context": "http://vocab.odpt.org/context_odpt.jsonld",
    "dct:issued": "2023-03-18",
    "owl:sameAs": "odpt.RailwayFare:Tokyu.Ikegami.Yukigayaotsuka.Tokyu.Ikegami.Ikegami",
    "odpt:operator": "odpt.Operator:Tokyu",
    "odpt:toStation": "odpt.Station:Tokyu.Ikegami.Ikegami",
    "odpt:icCardFare": 180,
    "odpt:ticketFare": 180,
    "odpt:fromStation": "odpt.Station:Tokyu.Ikegami.Yukigayaotsuka",
    "odpt:childIcCardFare": 90,
    "odpt:childTicketFare": 90
  },
  {
    "@id": "urn:ucode:_00001C0000000000000100000317A5A4",
    "@type": "odpt:RailwayFare",
    "dc:date": "2025-06-30T15:00:00+09:00",
    "@context": "http://vocab.odpt.org/context_odpt.jsonld",
    "dct:issued": "2023-03-18",
    "owl:sameAs": "odpt.RailwayFare:Tokyu.Ikegami.Yukigayaotsuka.Tokyu.Ikegami.IshikawaDai",
    "odpt:operator": "odpt.Operator:Tokyu",
    "odpt:toStation": "odpt.Station:Tokyu.Ikegami.IshikawaDai",
    "odpt:icCardFare": 140,
    "odpt:ticketFare": 140,
    "odpt:fromStation": "odpt.Station:Tokyu.Ikegami.Yukigayaotsuka",
    "odpt:childIcCardFare": 70,
    "odpt:childTicketFare": 70
  },
  {
    "@id": "urn:ucode:_00001C0000000000000100000317A5A5",
    "@type": "odpt:RailwayFare",
    "dc:date": "2025-06-30T15:00:00+09:00",
    "@context": "http://vocab.odpt.org/context_odpt.jsonld",
    "dct:issued": "2023-03-18",
    "owl:sameAs": "odpt.RailwayFare:Tokyu.Ikegami.Yukigayaotsuka.Tokyu.Ikegami.Kamata",
    "odpt:operator": "odpt.Operator:Tokyu",
    "odpt:toStation": "odpt.Station:Tokyu.Ikegami.Kamata",
    "odpt:icCardFare": 180,
    "odpt:ticketFare": 180,
    "odpt:fromStation": "odpt.Station:Tokyu.Ikegami.Yukigayaotsuka",
    "odpt:childIcCardFare": 90,
    "odpt:childTicketFare": 90
  },
  {
    "@id": "urn:ucode:_00001C0000000000000100000317A5A6",
    "@type": "odpt:RailwayFare",
    "dc:date": "2025-06-30T15:00:00+09:00",
    "@context": "http://vocab.odpt.org/context_odpt.jsonld",
    "dct:issued": "2023-03-18",
    "owl:sameAs": "odpt.RailwayFare:Tokyu.Ikegami.Yukigayaotsuka.Tokyu.Ikegami.Kugahara",
    "odpt:operator": "odpt.Operator:Tokyu",
    "odpt:toStation": "odpt.Station:Tokyu.Ikegami.Kugahara",
    "odpt:icCardFare": 140,
    "odpt:ticketFare": 140,
    "odpt:fromStation": "odpt.Station:Tokyu.Ikegami.Yukigayaotsuka",
    "odpt:childIcCardFare": 70,
    "odpt:childTicketFare": 70
  },
  {
    "@id": "urn:ucode:_00001C0000000000000100000317A5A7",
    "@type": "odpt:RailwayFare",
    "dc:date": "2025-06-30T15:00:00+09:00",
    "@context": "http://vocab.odpt.org/context_odpt.jsonld",
    "dct:issued": "2023-03-18",
    "owl:sameAs": "odpt.RailwayFare:Tokyu.Ikegami.Yukigayaotsuka.Tokyu.Ikegami.Nagahara",
    "odpt:operator": "odpt.Operator:Tokyu",
    "odpt:toStation": "odpt.Station:Tokyu.Ikegami.Nagahara",
    "odpt:icCardFare": 140,
    "odpt:ticketFare": 140,
    "odpt:fromStation": "odpt.Station:Tokyu.Ikegami.Yukigayaotsuka",
    "odpt:childIcCardFare": 70,
    "odpt:childTicketFare": 70
  },
  {
    "@id": "urn:ucode:_00001C0000000000000100000317A5A8",
    "@type": "odpt:RailwayFare",
    "dc:date": "2025-06-30T15:00:00+09:00",
    "@context": "http://vocab.odpt.org/context_odpt.jsonld",
    "dct:issued": "2023-03-18",
    "owl:sameAs": "odpt.RailwayFare:Tokyu.Ikegami.Yukigayaotsuka.Tokyu.Ikegami.Ontakesan",
    "odpt:operator": "odpt.Operator:Tokyu",
    "odpt:toStation": "odpt.Station:Tokyu.Ikegami.Ontakesan",
    "odpt:icCardFare": 140,
    "odpt:ticketFare": 140,
    "odpt:fromStation": "odpt.Station:Tokyu.Ikegami.Yukigayaotsuka",
    "odpt:childIcCardFare": 70,
    "odpt:childTicketFare": 70
  },
  {
    "@id": "urn:ucode:_00001C0000000000000100000317A5A9",
    "@type": "odpt:RailwayFare",
    "dc:date": "2025-06-30T15:00:00+09:00",
    "@context": "http://vocab.odpt.org/context_odpt.jsonld",
    "dct:issued": "2023-03-18",
    "owl:sameAs": "odpt.RailwayFare:Tokyu.Ikegami.Yukigayaotsuka.Tokyu.Ikegami.Osakihirokoji",
    "odpt:operator": "odpt.Operator:Tokyu",
    "odpt:toStation": "odpt.Station:Tokyu.Ikegami.Osakihirokoji",
    "odpt:icCardFare": 180,
    "odpt:ticketFare": 180,
    "odpt:fromStation": "odpt.Station:Tokyu.Ikegami.Yukigayaotsuka",
    "odpt:childIcCardFare": 90,
    "odpt:childTicketFare": 90
  },
  {
    "@id": "urn:ucode:_00001C0000000000000100000317A5AA",
    "@type": "odpt:RailwayFare",
    "dc:date": "2025-06-30T15:00:00+09:00",
    "@context": "http://vocab.odpt.org/context_odpt.jsonld",
    "dct:issued": "2023-03-18",
    "owl:sameAs": "odpt.RailwayFare:Tokyu.Ikegami.Yukigayaotsuka.Tokyu.Ikegami.SenzokuIke",
    "odpt:operator": "odpt.Operator:Tokyu",
    "odpt:toStation": "odpt.Station:Tokyu.Ikegami.SenzokuIke",
    "odpt:icCardFare": 140,
    "odpt:ticketFare": 140,
    "odpt:fromStation": "odpt.Station:Tokyu.Ikegami.Yukigayaotsuka",
    "odpt:childIcCardFare": 70,
    "odpt:childTicketFare": 70
  },
  {
    "@id": "urn:ucode:_00001C0000000000000100000317A5AB",
    "@type": "odpt:RailwayFare",
    "dc:date": "2025-06-30T15:00:00+09:00",
    "@context": "http://vocab.odpt.org/context_odpt.jsonld",
    "dct:issued": "2023-03-18",
    "owl:sameAs": "odpt.RailwayFare:Tokyu.Ikegami.Yukigayaotsuka.Tokyu.Ikegami.TogoshiGinza",
    "odpt:operator": "odpt.Operator:Tokyu",
    "odpt:toStation": "odpt.Station:Tokyu.Ikegami.TogoshiGinza",
    "odpt:icCardFare": 180,
    "odpt:ticketFare": 180,
    "odpt:fromStation": "odpt.Station:Tokyu.Ikegami.Yukigayaotsuka",
    "odpt:childIcCardFare": 90,
    "odpt:childTicketFare": 90
  },
  {
    "@id": "urn:ucode:_00001C0000000000000100000317A5AC",
    "@type": "odpt:RailwayFare",
    "dc:date": "2025-06-30T15:00:00+09:00",
    "@context": "http://vocab.odpt.org/context_odpt.jsonld",
    "dct:issued": "2023-03-18",
    "owl:sameAs": "odpt.RailwayFare:Tokyu.Ikegami.Yukigayaotsuka.Tokyu.Kodomonokuni.Kodomonokuni",
    "odpt:operator": "odpt.Operator:Tokyu",
    "odpt:toStation": "odpt.Station:Tokyu.Kodomonokuni.Kodomonokuni",
    "odpt:icCardFare": 504,
    "odpt:ticketFare": 510,
    "odpt:fromStation": "odpt.Station:Tokyu.Ikegami.Yukigayaotsuka",
    "odpt:childIcCardFare": 251,
    "odpt:childTicketFare": 260
  },
  {
    "@id": "urn:ucode:_00001C0000000000000100000317A5AD",
    "@type": "odpt:RailwayFare",
    "dc:date": "2025-06-30T15:00:00+09:00",
    "@context": "http://vocab.odpt.org/context_odpt.jsonld",
    "dct:issued": "2023-03-18",
    "owl:sameAs": "odpt.RailwayFare:Tokyu.Ikegami.Yukigayaotsuka.Tokyu.Kodomonokuni.Nagatsuta",
    "odpt:operator": "odpt.Operator:Tokyu",
    "odpt:toStation": "odpt.Station:Tokyu.Kodomonokuni.Nagatsuta",
    "odpt:icCardFare": 347,
    "odpt:ticketFare": 350,
    "odpt:fromStation": "odpt.Station:Tokyu.Ikegami.Yukigayaotsuka",
    "odpt:childIcCardFare": 173,
    "odpt:childTicketFare": 180
  },
  {
    "@id": "urn:ucode:_00001C0000000000000100000317A5AE",
    "@type": "odpt:RailwayFare",
    "dc:date": "2025-06-30T15:00:00+09:00",
    "@context": "http://vocab.odpt.org/context_odpt.jsonld",
    "dct:issued": "2023-03-18",
    "owl:sameAs": "odpt.RailwayFare:Tokyu.Ikegami.Yukigayaotsuka.Tokyu.Kodomonokuni.Onda",
    "odpt:operator": "odpt.Operator:Tokyu",
    "odpt:toStation": "odpt.Station:Tokyu.Kodomonokuni.Onda",
    "odpt:icCardFare": 504,
    "odpt:ticketFare": 510,
    "odpt:fromStation": "odpt.Station:Tokyu.Ikegami.Yukigayaotsuka",
    "odpt:childIcCardFare": 251,
    "odpt:childTicketFare": 260
  },
  {
    "@id": "urn:ucode:_00001C0000000000000100000317A5AF",
    "@type": "odpt:RailwayFare",
    "dc:date": "2025-06-30T15:00:00+09:00",
    "@context": "http://vocab.odpt.org/context_odpt.jsonld",
    "dct:issued": "2023-03-18",
    "owl:sameAs": "odpt.RailwayFare:Tokyu.Ikegami.Yukigayaotsuka.Tokyu.Meguro.DenEnChofu",
    "odpt:operator": "odpt.Operator:Tokyu",
    "odpt:toStation": "odpt.Station:Tokyu.Meguro.DenEnChofu",
    "odpt:icCardFare": 180,
    "odpt:ticketFare": 180,
    "odpt:fromStation": "odpt.Station:Tokyu.Ikegami.Yukigayaotsuka",
    "odpt:childIcCardFare": 90,
    "odpt:childTicketFare": 90
  },
  {
    "@id": "urn:ucode:_00001C0000000000000100000317A5B0",
    "@type": "odpt:RailwayFare",
    "dc:date": "2025-06-30T15:00:00+09:00",
    "@context": "http://vocab.odpt.org/context_odpt.jsonld",
    "dct:issued": "2023-03-18",
    "owl:sameAs": "odpt.RailwayFare:Tokyu.Ikegami.Yukigayaotsuka.Tokyu.Meguro.FudoMae",
    "odpt:operator": "odpt.Operator:Tokyu",
    "odpt:toStation": "odpt.Station:Tokyu.Meguro.FudoMae",
    "odpt:icCardFare": 227,
    "odpt:ticketFare": 230,
    "odpt:fromStation": "odpt.Station:Tokyu.Ikegami.Yukigayaotsuka",
    "odpt:childIcCardFare": 113,
    "odpt:childTicketFare": 120
  },
  {
    "@id": "urn:ucode:_00001C0000000000000100000317A5B1",
    "@type": "odpt:RailwayFare",
    "dc:date": "2025-06-30T15:00:00+09:00",
    "@context": "http://vocab.odpt.org/context_odpt.jsonld",
    "dct:issued": "2023-03-18",
    "owl:sameAs": "odpt.RailwayFare:Tokyu.Ikegami.Yukigayaotsuka.Tokyu.Meguro.Hiyoshi",
    "odpt:operator": "odpt.Operator:Tokyu",
    "odpt:toStation": "odpt.Station:Tokyu.Meguro.Hiyoshi",
    "odpt:icCardFare": 250,
    "odpt:ticketFare": 250,
    "odpt:fromStation": "odpt.Station:Tokyu.Ikegami.Yukigayaotsuka",
    "odpt:childIcCardFare": 125,
    "odpt:childTicketFare": 130
  },
  {
    "@id": "urn:ucode:_00001C0000000000000100000317A5B2",
    "@type": "odpt:RailwayFare",
    "dc:date": "2025-06-30T15:00:00+09:00",
    "@context": "http://vocab.odpt.org/context_odpt.jsonld",
    "dct:issued": "2023-03-18",
    "owl:sameAs": "odpt.RailwayFare:Tokyu.Ikegami.Yukigayaotsuka.Tokyu.Meguro.Meguro",
    "odpt:operator": "odpt.Operator:Tokyu",
    "odpt:toStation": "odpt.Station:Tokyu.Meguro.Meguro",
    "odpt:icCardFare": 227,
    "odpt:ticketFare": 230,
    "odpt:fromStation": "odpt.Station:Tokyu.Ikegami.Yukigayaotsuka",
    "odpt:childIcCardFare": 113,
    "odpt:childTicketFare": 120
  },
  {
    "@id": "urn:ucode:_00001C0000000000000100000317A5B3",
    "@type": "odpt:RailwayFare",
    "dc:date": "2025-06-30T15:00:00+09:00",
    "@context": "http://vocab.odpt.org/context_odpt.jsonld",
    "dct:issued": "2023-03-18",
    "owl:sameAs": "odpt.RailwayFare:Tokyu.Ikegami.Yukigayaotsuka.Tokyu.Meguro.Motosumiyoshi",
    "odpt:operator": "odpt.Operator:Tokyu",
    "odpt:toStation": "odpt.Station:Tokyu.Meguro.Motosumiyoshi",
    "odpt:icCardFare": 227,
    "odpt:ticketFare": 230,
    "odpt:fromStation": "odpt.Station:Tokyu.Ikegami.Yukigayaotsuka",
    "odpt:childIcCardFare": 113,
    "odpt:childTicketFare": 120
  },
  {
    "@id": "urn:ucode:_00001C0000000000000100000317A5B4",
    "@type": "odpt:RailwayFare",
    "dc:date": "2025-06-30T15:00:00+09:00",
    "@context": "http://vocab.odpt.org/context_odpt.jsonld",
    "dct:issued": "2023-03-18",
    "owl:sameAs": "odpt.RailwayFare:Tokyu.Ikegami.Yukigayaotsuka.Tokyu.Meguro.MusashiKosugi",
    "odpt:operator": "odpt.Operator:Tokyu",
    "odpt:toStation": "odpt.Station:Tokyu.Meguro.MusashiKosugi",
    "odpt:icCardFare": 227,
    "odpt:ticketFare": 230,
    "odpt:fromStation": "odpt.Station:Tokyu.Ikegami.Yukigayaotsuka",
    "odpt:childIcCardFare": 113,
    "odpt:childTicketFare": 120
  },
  {
    "@id": "urn:ucode:_00001C0000000000000100000317A5B5",
    "@type": "odpt:RailwayFare",
    "dc:date": "2025-06-30T15:00:00+09:00",
    "@context": "http://vocab.odpt.org/context_odpt.jsonld",
    "dct:issued": "2023-03-18",
    "owl:sameAs": "odpt.RailwayFare:Tokyu.Ikegami.Yukigayaotsuka.Tokyu.Meguro.MusashiKoyama",
    "odpt:operator": "odpt.Operator:Tokyu",
    "odpt:toStation": "odpt.Station:Tokyu.Meguro.MusashiKoyama",
    "odpt:icCardFare": 180,
    "odpt:ticketFare": 180,
    "odpt:fromStation": "odpt.Station:Tokyu.Ikegami.Yukigayaotsuka",
    "odpt:childIcCardFare": 90,
    "odpt:childTicketFare": 90
  },
  {
    "@id": "urn:ucode:_00001C0000000000000100000317A5B6",
    "@type": "odpt:RailwayFare",
    "dc:date": "2025-06-30T15:00:00+09:00",
    "@context": "http://vocab.odpt.org/context_odpt.jsonld",
    "dct:issued": "2023-03-18",
    "owl:sameAs": "odpt.RailwayFare:Tokyu.Ikegami.Yukigayaotsuka.Tokyu.Meguro.NishiKoyama",
    "odpt:operator": "odpt.Operator:Tokyu",
    "odpt:toStation": "odpt.Station:Tokyu.Meguro.NishiKoyama",
    "odpt:icCardFare": 180,
    "odpt:ticketFare": 180,
    "odpt:fromStation": "odpt.Station:Tokyu.Ikegami.Yukigayaotsuka",
    "odpt:childIcCardFare": 90,
    "odpt:childTicketFare": 90
  },
  {
    "@id": "urn:ucode:_00001C0000000000000100000317A5B7",
    "@type": "odpt:RailwayFare",
    "dc:date": "2025-06-30T15:00:00+09:00",
    "@context": "http://vocab.odpt.org/context_odpt.jsonld",
    "dct:issued": "2023-03-18",
    "owl:sameAs": "odpt.RailwayFare:Tokyu.Ikegami.Yukigayaotsuka.Tokyu.Meguro.Okusawa",
    "odpt:operator": "odpt.Operator:Tokyu",
    "odpt:toStation": "odpt.Station:Tokyu.Meguro.Okusawa",
    "odpt:icCardFare": 180,
    "odpt:ticketFare": 180,
    "odpt:fromStation": "odpt.Station:Tokyu.Ikegami.Yukigayaotsuka",
    "odpt:childIcCardFare": 90,
    "odpt:childTicketFare": 90
  },
  {
    "@id": "urn:ucode:_00001C0000000000000100000317A5B8",
    "@type": "odpt:RailwayFare",
    "dc:date": "2025-06-30T15:00:00+09:00",
    "@context": "http://vocab.odpt.org/context_odpt.jsonld",
    "dct:issued": "2023-03-18",
    "owl:sameAs": "odpt.RailwayFare:Tokyu.Ikegami.Yukigayaotsuka.Tokyu.Meguro.Ookayama",
    "odpt:operator": "odpt.Operator:Tokyu",
    "odpt:toStation": "odpt.Station:Tokyu.Meguro.Ookayama",
    "odpt:icCardFare": 180,
    "odpt:ticketFare": 180,
    "odpt:fromStation": "odpt.Station:Tokyu.Ikegami.Yukigayaotsuka",
    "odpt:childIcCardFare": 90,
    "odpt:childTicketFare": 90
  },
  {
    "@id": "urn:ucode:_00001C0000000000000100000317A5B9",
    "@type": "odpt:RailwayFare",
    "dc:date": "2025-06-30T15:00:00+09:00",
    "@context": "http://vocab.odpt.org/context_odpt.jsonld",
    "dct:issued": "2023-03-18",
    "owl:sameAs": "odpt.RailwayFare:Tokyu.Ikegami.Yukigayaotsuka.Tokyu.Meguro.Senzoku",
    "odpt:operator": "odpt.Operator:Tokyu",
    "odpt:toStation": "odpt.Station:Tokyu.Meguro.Senzoku",
    "odpt:icCardFare": 180,
    "odpt:ticketFare": 180,
    "odpt:fromStation": "odpt.Station:Tokyu.Ikegami.Yukigayaotsuka",
    "odpt:childIcCardFare": 90,
    "odpt:childTicketFare": 90
  },
  {
    "@id": "urn:ucode:_00001C0000000000000100000317A5BA",
    "@type": "odpt:RailwayFare",
    "dc:date": "2025-06-30T15:00:00+09:00",
    "@context": "http://vocab.odpt.org/context_odpt.jsonld",
    "dct:issued": "2023-03-18",
    "owl:sameAs": "odpt.RailwayFare:Tokyu.Ikegami.Yukigayaotsuka.Tokyu.Meguro.ShinMaruko",
    "odpt:operator": "odpt.Operator:Tokyu",
    "odpt:toStation": "odpt.Station:Tokyu.Meguro.ShinMaruko",
    "odpt:icCardFare": 227,
    "odpt:ticketFare": 230,
    "odpt:fromStation": "odpt.Station:Tokyu.Ikegami.Yukigayaotsuka",
    "odpt:childIcCardFare": 113,
    "odpt:childTicketFare": 120
  },
  {
    "@id": "urn:ucode:_00001C0000000000000100000317A5BB",
    "@type": "odpt:RailwayFare",
    "dc:date": "2025-06-30T15:00:00+09:00",
    "@context": "http://vocab.odpt.org/context_odpt.jsonld",
    "dct:issued": "2023-03-18",
    "owl:sameAs": "odpt.RailwayFare:Tokyu.Ikegami.Yukigayaotsuka.Tokyu.Meguro.Tamagawa",
    "odpt:operator": "odpt.Operator:Tokyu",
    "odpt:toStation": "odpt.Station:Tokyu.Meguro.Tamagawa",
    "odpt:icCardFare": 227,
    "odpt:ticketFare": 230,
    "odpt:fromStation": "odpt.Station:Tokyu.Ikegami.Yukigayaotsuka",
    "odpt:childIcCardFare": 113,
    "odpt:childTicketFare": 120
  },
  {
    "@id": "urn:ucode:_00001C0000000000000100000317A5BC",
    "@type": "odpt:RailwayFare",
    "dc:date": "2025-06-30T15:00:00+09:00",
    "@context": "http://vocab.odpt.org/context_odpt.jsonld",
    "dct:issued": "2023-03-18",
    "owl:sameAs": "odpt.RailwayFare:Tokyu.Ikegami.Yukigayaotsuka.Tokyu.Oimachi.EbaraMachi",
    "odpt:operator": "odpt.Operator:Tokyu",
    "odpt:toStation": "odpt.Station:Tokyu.Oimachi.EbaraMachi",
    "odpt:icCardFare": 140,
    "odpt:ticketFare": 140,
    "odpt:fromStation": "odpt.Station:Tokyu.Ikegami.Yukigayaotsuka",
    "odpt:childIcCardFare": 70,
    "odpt:childTicketFare": 70
  },
  {
    "@id": "urn:ucode:_00001C0000000000000100000317A5BD",
    "@type": "odpt:RailwayFare",
    "dc:date": "2025-06-30T15:00:00+09:00",
    "@context": "http://vocab.odpt.org/context_odpt.jsonld",
    "dct:issued": "2023-03-18",
    "owl:sameAs": "odpt.RailwayFare:Tokyu.Ikegami.Yukigayaotsuka.Tokyu.Oimachi.FutakoTamagawa",
    "odpt:operator": "odpt.Operator:Tokyu",
    "odpt:toStation": "odpt.Station:Tokyu.Oimachi.FutakoTamagawa",
    "odpt:icCardFare": 227,
    "odpt:ticketFare": 230,
    "odpt:fromStation": "odpt.Station:Tokyu.Ikegami.Yukigayaotsuka",
    "odpt:childIcCardFare": 113,
    "odpt:childTicketFare": 120
  },
  {
    "@id": "urn:ucode:_00001C0000000000000100000317A5BE",
    "@type": "odpt:RailwayFare",
    "dc:date": "2025-06-30T15:00:00+09:00",
    "@context": "http://vocab.odpt.org/context_odpt.jsonld",
    "dct:issued": "2023-03-18",
    "owl:sameAs": "odpt.RailwayFare:Tokyu.Ikegami.Yukigayaotsuka.Tokyu.Oimachi.Hatanodai",
    "odpt:operator": "odpt.Operator:Tokyu",
    "odpt:toStation": "odpt.Station:Tokyu.Oimachi.Hatanodai",
    "odpt:icCardFare": 140,
    "odpt:ticketFare": 140,
    "odpt:fromStation": "odpt.Station:Tokyu.Ikegami.Yukigayaotsuka",
    "odpt:childIcCardFare": 70,
    "odpt:childTicketFare": 70
  },
  {
    "@id": "urn:ucode:_00001C0000000000000100000317A5BF",
    "@type": "odpt:RailwayFare",
    "dc:date": "2025-06-30T15:00:00+09:00",
    "@context": "http://vocab.odpt.org/context_odpt.jsonld",
    "dct:issued": "2023-03-18",
    "owl:sameAs": "odpt.RailwayFare:Tokyu.Ikegami.Yukigayaotsuka.Tokyu.Oimachi.Jiyugaoka",
    "odpt:operator": "odpt.Operator:Tokyu",
    "odpt:toStation": "odpt.Station:Tokyu.Oimachi.Jiyugaoka",
    "odpt:icCardFare": 180,
    "odpt:ticketFare": 180,
    "odpt:fromStation": "odpt.Station:Tokyu.Ikegami.Yukigayaotsuka",
    "odpt:childIcCardFare": 90,
    "odpt:childTicketFare": 90
  },
  {
    "@id": "urn:ucode:_00001C0000000000000100000317A5C0",
    "@type": "odpt:RailwayFare",
    "dc:date": "2025-06-30T15:00:00+09:00",
    "@context": "http://vocab.odpt.org/context_odpt.jsonld",
    "dct:issued": "2023-03-18",
    "owl:sameAs": "odpt.RailwayFare:Tokyu.Ikegami.Yukigayaotsuka.Tokyu.Oimachi.Kaminoge",
    "odpt:operator": "odpt.Operator:Tokyu",
    "odpt:toStation": "odpt.Station:Tokyu.Oimachi.Kaminoge",
    "odpt:icCardFare": 227,
    "odpt:ticketFare": 230,
    "odpt:fromStation": "odpt.Station:Tokyu.Ikegami.Yukigayaotsuka",
    "odpt:childIcCardFare": 113,
    "odpt:childTicketFare": 120
  },
  {
    "@id": "urn:ucode:_00001C0000000000000100000317A5C1",
    "@type": "odpt:RailwayFare",
    "dc:date": "2025-06-30T15:00:00+09:00",
    "@context": "http://vocab.odpt.org/context_odpt.jsonld",
    "dct:issued": "2023-03-18",
    "owl:sameAs": "odpt.RailwayFare:Tokyu.Ikegami.Yukigayaotsuka.Tokyu.Oimachi.KitaSenzoku",
    "odpt:operator": "odpt.Operator:Tokyu",
    "odpt:toStation": "odpt.Station:Tokyu.Oimachi.KitaSenzoku",
    "odpt:icCardFare": 180,
    "odpt:ticketFare": 180,
    "odpt:fromStation": "odpt.Station:Tokyu.Ikegami.Yukigayaotsuka",
    "odpt:childIcCardFare": 90,
    "odpt:childTicketFare": 90
  },
  {
    "@id": "urn:ucode:_00001C0000000000000100000317A5C2",
    "@type": "odpt:RailwayFare",
    "dc:date": "2025-06-30T15:00:00+09:00",
    "@context": "http://vocab.odpt.org/context_odpt.jsonld",
    "dct:issued": "2023-03-18",
    "owl:sameAs": "odpt.RailwayFare:Tokyu.Ikegami.Yukigayaotsuka.Tokyu.Oimachi.Kuhombutsu",
    "odpt:operator": "odpt.Operator:Tokyu",
    "odpt:toStation": "odpt.Station:Tokyu.Oimachi.Kuhombutsu",
    "odpt:icCardFare": 180,
    "odpt:ticketFare": 180,
    "odpt:fromStation": "odpt.Station:Tokyu.Ikegami.Yukigayaotsuka",
    "odpt:childIcCardFare": 90,
    "odpt:childTicketFare": 90
  },
  {
    "@id": "urn:ucode:_00001C0000000000000100000317A5C3",
    "@type": "odpt:RailwayFare",
    "dc:date": "2025-06-30T15:00:00+09:00",
    "@context": "http://vocab.odpt.org/context_odpt.jsonld",
    "dct:issued": "2023-03-18",
    "owl:sameAs": "odpt.RailwayFare:Tokyu.Ikegami.Yukigayaotsuka.Tokyu.Oimachi.Midorigaoka",
    "odpt:operator": "odpt.Operator:Tokyu",
    "odpt:toStation": "odpt.Station:Tokyu.Oimachi.Midorigaoka",
    "odpt:icCardFare": 180,
    "odpt:ticketFare": 180,
    "odpt:fromStation": "odpt.Station:Tokyu.Ikegami.Yukigayaotsuka",
    "odpt:childIcCardFare": 90,
    "odpt:childTicketFare": 90
  },
  {
    "@id": "urn:ucode:_00001C0000000000000100000317A5C4",
    "@type": "odpt:RailwayFare",
    "dc:date": "2025-06-30T15:00:00+09:00",
    "@context": "http://vocab.odpt.org/context_odpt.jsonld",
    "dct:issued": "2023-03-18",
    "owl:sameAs": "odpt.RailwayFare:Tokyu.Ikegami.Yukigayaotsuka.Tokyu.Oimachi.Mizonokuchi",
    "odpt:operator": "odpt.Operator:Tokyu",
    "odpt:toStation": "odpt.Station:Tokyu.Oimachi.Mizonokuchi",
    "odpt:icCardFare": 250,
    "odpt:ticketFare": 250,
    "odpt:fromStation": "odpt.Station:Tokyu.Ikegami.Yukigayaotsuka",
    "odpt:childIcCardFare": 125,
    "odpt:childTicketFare": 130
  },
  {
    "@id": "urn:ucode:_00001C0000000000000100000317A5C5",
    "@type": "odpt:RailwayFare",
    "dc:date": "2025-06-30T15:00:00+09:00",
    "@context": "http://vocab.odpt.org/context_odpt.jsonld",
    "dct:issued": "2023-03-18",
    "owl:sameAs": "odpt.RailwayFare:Tokyu.Ikegami.Yukigayaotsuka.Tokyu.Oimachi.Nakanobu",
    "odpt:operator": "odpt.Operator:Tokyu",
    "odpt:toStation": "odpt.Station:Tokyu.Oimachi.Nakanobu",
    "odpt:icCardFare": 180,
    "odpt:ticketFare": 180,
    "odpt:fromStation": "odpt.Station:Tokyu.Ikegami.Yukigayaotsuka",
    "odpt:childIcCardFare": 90,
    "odpt:childTicketFare": 90
  },
  {
    "@id": "urn:ucode:_00001C0000000000000100000317A5C6",
    "@type": "odpt:RailwayFare",
    "dc:date": "2025-06-30T15:00:00+09:00",
    "@context": "http://vocab.odpt.org/context_odpt.jsonld",
    "dct:issued": "2023-03-18",
    "owl:sameAs": "odpt.RailwayFare:Tokyu.Ikegami.Yukigayaotsuka.Tokyu.Oimachi.Oimachi",
    "odpt:operator": "odpt.Operator:Tokyu",
    "odpt:toStation": "odpt.Station:Tokyu.Oimachi.Oimachi",
    "odpt:icCardFare": 180,
    "odpt:ticketFare": 180,
    "odpt:fromStation": "odpt.Station:Tokyu.Ikegami.Yukigayaotsuka",
    "odpt:childIcCardFare": 90,
    "odpt:childTicketFare": 90
  },
  {
    "@id": "urn:ucode:_00001C0000000000000100000317A5C7",
    "@type": "odpt:RailwayFare",
    "dc:date": "2025-06-30T15:00:00+09:00",
    "@context": "http://vocab.odpt.org/context_odpt.jsonld",
    "dct:issued": "2023-03-18",
    "owl:sameAs": "odpt.RailwayFare:Tokyu.Ikegami.Yukigayaotsuka.Tokyu.Oimachi.Ookayama",
    "odpt:operator": "odpt.Operator:Tokyu",
    "odpt:toStation": "odpt.Station:Tokyu.Oimachi.Ookayama",
    "odpt:icCardFare": 180,
    "odpt:ticketFare": 180,
    "odpt:fromStation": "odpt.Station:Tokyu.Ikegami.Yukigayaotsuka",
    "odpt:childIcCardFare": 90,
    "odpt:childTicketFare": 90
  },
  {
    "@id": "urn:ucode:_00001C0000000000000100000317A5C8",
    "@type": "odpt:RailwayFare",
    "dc:date": "2025-06-30T15:00:00+09:00",
    "@context": "http://vocab.odpt.org/context_odpt.jsonld",
    "dct:issued": "2023-03-18",
    "owl:sameAs": "odpt.RailwayFare:Tokyu.Ikegami.Yukigayaotsuka.Tokyu.Oimachi.Oyamadai",
    "odpt:operator": "odpt.Operator:Tokyu",
    "odpt:toStation": "odpt.Station:Tokyu.Oimachi.Oyamadai",
    "odpt:icCardFare": 227,
    "odpt:ticketFare": 230,
    "odpt:fromStation": "odpt.Station:Tokyu.Ikegami.Yukigayaotsuka",
    "odpt:childIcCardFare": 113,
    "odpt:childTicketFare": 120
  },
  {
    "@id": "urn:ucode:_00001C0000000000000100000317A5C9",
    "@type": "odpt:RailwayFare",
    "dc:date": "2025-06-30T15:00:00+09:00",
    "@context": "http://vocab.odpt.org/context_odpt.jsonld",
    "dct:issued": "2023-03-18",
    "owl:sameAs": "odpt.RailwayFare:Tokyu.Ikegami.Yukigayaotsuka.Tokyu.Oimachi.ShimoShimmei",
    "odpt:operator": "odpt.Operator:Tokyu",
    "odpt:toStation": "odpt.Station:Tokyu.Oimachi.ShimoShimmei",
    "odpt:icCardFare": 180,
    "odpt:ticketFare": 180,
    "odpt:fromStation": "odpt.Station:Tokyu.Ikegami.Yukigayaotsuka",
    "odpt:childIcCardFare": 90,
    "odpt:childTicketFare": 90
  },
  {
    "@id": "urn:ucode:_00001C0000000000000100000317A5CA",
    "@type": "odpt:RailwayFare",
    "dc:date": "2025-06-30T15:00:00+09:00",
    "@context": "http://vocab.odpt.org/context_odpt.jsonld",
    "dct:issued": "2023-03-18",
    "owl:sameAs": "odpt.RailwayFare:Tokyu.Ikegami.Yukigayaotsuka.Tokyu.Oimachi.Todoroki",
    "odpt:operator": "odpt.Operator:Tokyu",
    "odpt:toStation": "odpt.Station:Tokyu.Oimachi.Todoroki",
    "odpt:icCardFare": 227,
    "odpt:ticketFare": 230,
    "odpt:fromStation": "odpt.Station:Tokyu.Ikegami.Yukigayaotsuka",
    "odpt:childIcCardFare": 113,
    "odpt:childTicketFare": 120
  },
  {
    "@id": "urn:ucode:_00001C0000000000000100000317A5CB",
    "@type": "odpt:RailwayFare",
    "dc:date": "2025-06-30T15:00:00+09:00",
    "@context": "http://vocab.odpt.org/context_odpt.jsonld",
    "dct:issued": "2023-03-18",
    "owl:sameAs": "odpt.RailwayFare:Tokyu.Ikegami.Yukigayaotsuka.Tokyu.Oimachi.TogoshiKoen",
    "odpt:operator": "odpt.Operator:Tokyu",
    "odpt:toStation": "odpt.Station:Tokyu.Oimachi.TogoshiKoen",
    "odpt:icCardFare": 180,
    "odpt:ticketFare": 180,
    "odpt:fromStation": "odpt.Station:Tokyu.Ikegami.Yukigayaotsuka",
    "odpt:childIcCardFare": 90,
    "odpt:childTicketFare": 90
  },
  {
    "@id": "urn:ucode:_00001C0000000000000100000317A5CC",
    "@type": "odpt:RailwayFare",
    "dc:date": "2025-06-30T15:00:00+09:00",
    "@context": "http://vocab.odpt.org/context_odpt.jsonld",
    "dct:issued": "2023-03-18",
    "owl:sameAs": "odpt.RailwayFare:Tokyu.Ikegami.Yukigayaotsuka.Tokyu.Setagaya.Kamimachi",
    "odpt:operator": "odpt.Operator:Tokyu",
    "odpt:toStation": "odpt.Station:Tokyu.Setagaya.Kamimachi",
    "odpt:icCardFare": 448,
    "odpt:ticketFare": 450,
    "odpt:fromStation": "odpt.Station:Tokyu.Ikegami.Yukigayaotsuka",
    "odpt:childIcCardFare": 224,
    "odpt:childTicketFare": 230
  },
  {
    "@id": "urn:ucode:_00001C0000000000000100000317A5CD",
    "@type": "odpt:RailwayFare",
    "dc:date": "2025-06-30T15:00:00+09:00",
    "@context": "http://vocab.odpt.org/context_odpt.jsonld",
    "dct:issued": "2023-03-18",
    "owl:sameAs": "odpt.RailwayFare:Tokyu.Ikegami.Yukigayaotsuka.Tokyu.Setagaya.Matsubara",
    "odpt:operator": "odpt.Operator:Tokyu",
    "odpt:toStation": "odpt.Station:Tokyu.Setagaya.Matsubara",
    "odpt:icCardFare": 448,
    "odpt:ticketFare": 450,
    "odpt:fromStation": "odpt.Station:Tokyu.Ikegami.Yukigayaotsuka",
    "odpt:childIcCardFare": 224,
    "odpt:childTicketFare": 230
  },
  {
    "@id": "urn:ucode:_00001C0000000000000100000317A5CE",
    "@type": "odpt:RailwayFare",
    "dc:date": "2025-06-30T15:00:00+09:00",
    "@context": "http://vocab.odpt.org/context_odpt.jsonld",
    "dct:issued": "2023-03-18",
    "owl:sameAs": "odpt.RailwayFare:Tokyu.Ikegami.Yukigayaotsuka.Tokyu.Setagaya.Miyanosaka",
    "odpt:operator": "odpt.Operator:Tokyu",
    "odpt:toStation": "odpt.Station:Tokyu.Setagaya.Miyanosaka",
    "odpt:icCardFare": 448,
    "odpt:ticketFare": 450,
    "odpt:fromStation": "odpt.Station:Tokyu.Ikegami.Yukigayaotsuka",
    "odpt:childIcCardFare": 224,
    "odpt:childTicketFare": 230
  },
  {
    "@id": "urn:ucode:_00001C0000000000000100000317A5CF",
    "@type": "odpt:RailwayFare",
    "dc:date": "2025-06-30T15:00:00+09:00",
    "@context": "http://vocab.odpt.org/context_odpt.jsonld",
    "dct:issued": "2023-03-18",
    "owl:sameAs": "odpt.RailwayFare:Tokyu.Ikegami.Yukigayaotsuka.Tokyu.Setagaya.NishiTaishido",
    "odpt:operator": "odpt.Operator:Tokyu",
    "odpt:toStation": "odpt.Station:Tokyu.Setagaya.NishiTaishido",
    "odpt:icCardFare": 448,
    "odpt:ticketFare": 450,
    "odpt:fromStation": "odpt.Station:Tokyu.Ikegami.Yukigayaotsuka",
    "odpt:childIcCardFare": 224,
    "odpt:childTicketFare": 230
  },
  {
    "@id": "urn:ucode:_00001C0000000000000100000317A5D0",
    "@type": "odpt:RailwayFare",
    "dc:date": "2025-06-30T15:00:00+09:00",
    "@context": "http://vocab.odpt.org/context_odpt.jsonld",
    "dct:issued": "2023-03-18",
    "owl:sameAs": "odpt.RailwayFare:Tokyu.Ikegami.Yukigayaotsuka.Tokyu.Setagaya.SangenJaya",
    "odpt:operator": "odpt.Operator:Tokyu",
    "odpt:toStation": "odpt.Station:Tokyu.Setagaya.SangenJaya",
    "odpt:icCardFare": 288,
    "odpt:ticketFare": 290,
    "odpt:fromStation": "odpt.Station:Tokyu.Ikegami.Yukigayaotsuka",
    "odpt:childIcCardFare": 144,
    "odpt:childTicketFare": 150
  },
  {
    "@id": "urn:ucode:_00001C0000000000000100000317A5D1",
    "@type": "odpt:RailwayFare",
    "dc:date": "2025-06-30T15:00:00+09:00",
    "@context": "http://vocab.odpt.org/context_odpt.jsonld",
    "dct:issued": "2023-03-18",
    "owl:sameAs": "odpt.RailwayFare:Tokyu.Ikegami.Yukigayaotsuka.Tokyu.Setagaya.Setagaya",
    "odpt:operator": "odpt.Operator:Tokyu",
    "odpt:toStation": "odpt.Station:Tokyu.Setagaya.Setagaya",
    "odpt:icCardFare": 448,
    "odpt:ticketFare": 450,
    "odpt:fromStation": "odpt.Station:Tokyu.Ikegami.Yukigayaotsuka",
    "odpt:childIcCardFare": 224,
    "odpt:childTicketFare": 230
  },
  {
    "@id": "urn:ucode:_00001C0000000000000100000317A5D2",
    "@type": "odpt:RailwayFare",
    "dc:date": "2025-06-30T15:00:00+09:00",
    "@context": "http://vocab.odpt.org/context_odpt.jsonld",
    "dct:issued": "2023-03-18",
    "owl:sameAs": "odpt.RailwayFare:Tokyu.Ikegami.Yukigayaotsuka.Tokyu.Setagaya.ShimoTakaido",
    "odpt:operator": "odpt.Operator:Tokyu",
    "odpt:toStation": "odpt.Station:Tokyu.Setagaya.ShimoTakaido",
    "odpt:icCardFare": 448,
    "odpt:ticketFare": 450,
    "odpt:fromStation": "odpt.Station:Tokyu.Ikegami.Yukigayaotsuka",
    "odpt:childIcCardFare": 224,
    "odpt:childTicketFare": 230
  },
  {
    "@id": "urn:ucode:_00001C0000000000000100000317A5D3",
    "@type": "odpt:RailwayFare",
    "dc:date": "2025-06-30T15:00:00+09:00",
    "@context": "http://vocab.odpt.org/context_odpt.jsonld",
    "dct:issued": "2023-03-18",
    "owl:sameAs": "odpt.RailwayFare:Tokyu.Ikegami.Yukigayaotsuka.Tokyu.Setagaya.ShoinJinjaMae",
    "odpt:operator": "odpt.Operator:Tokyu",
    "odpt:toStation": "odpt.Station:Tokyu.Setagaya.ShoinJinjaMae",
    "odpt:icCardFare": 448,
    "odpt:ticketFare": 450,
    "odpt:fromStation": "odpt.Station:Tokyu.Ikegami.Yukigayaotsuka",
    "odpt:childIcCardFare": 224,
    "odpt:childTicketFare": 230
  },
  {
    "@id": "urn:ucode:_00001C0000000000000100000317A5D4",
    "@type": "odpt:RailwayFare",
    "dc:date": "2025-06-30T15:00:00+09:00",
    "@context": "http://vocab.odpt.org/context_odpt.jsonld",
    "dct:issued": "2023-03-18",
    "owl:sameAs": "odpt.RailwayFare:Tokyu.Ikegami.Yukigayaotsuka.Tokyu.Setagaya.Wakabayashi",
    "odpt:operator": "odpt.Operator:Tokyu",
    "odpt:toStation": "odpt.Station:Tokyu.Setagaya.Wakabayashi",
    "odpt:icCardFare": 448,
    "odpt:ticketFare": 450,
    "odpt:fromStation": "odpt.Station:Tokyu.Ikegami.Yukigayaotsuka",
    "odpt:childIcCardFare": 224,
    "odpt:childTicketFare": 230
  },
  {
    "@id": "urn:ucode:_00001C0000000000000100000317A5D5",
    "@type": "odpt:RailwayFare",
    "dc:date": "2025-06-30T15:00:00+09:00",
    "@context": "http://vocab.odpt.org/context_odpt.jsonld",
    "dct:issued": "2023-03-18",
    "owl:sameAs": "odpt.RailwayFare:Tokyu.Ikegami.Yukigayaotsuka.Tokyu.Setagaya.Yamashita",
    "odpt:operator": "odpt.Operator:Tokyu",
    "odpt:toStation": "odpt.Station:Tokyu.Setagaya.Yamashita",
    "odpt:icCardFare": 448,
    "odpt:ticketFare": 450,
    "odpt:fromStation": "odpt.Station:Tokyu.Ikegami.Yukigayaotsuka",
    "odpt:childIcCardFare": 224,
    "odpt:childTicketFare": 230
  },
  {
    "@id": "urn:ucode:_00001C000000000000010000039A37BA",
    "@type": "odpt:RailwayFare",
    "dc:date": "2025-06-30T15:00:00+09:00",
    "@context": "http://vocab.odpt.org/context_odpt.jsonld",
    "dct:issued": "2023-03-18",
    "owl:sameAs": "odpt.RailwayFare:Tokyu.Ikegami.Yukigayaotsuka.Tokyu.TokyuShinYokohama.Hiyoshi",
    "odpt:operator": "odpt.Operator:Tokyu",
    "odpt:toStation": "odpt.Station:Tokyu.TokyuShinYokohama.Hiyoshi",
    "odpt:icCardFare": 250,
    "odpt:ticketFare": 250,
    "odpt:fromStation": "odpt.Station:Tokyu.Ikegami.Yukigayaotsuka",
    "odpt:childIcCardFare": 125,
    "odpt:childTicketFare": 130
  },
  {
    "@id": "urn:ucode:_00001C000000000000010000039A37BB",
    "@type": "odpt:RailwayFare",
    "dc:date": "2025-06-30T15:00:00+09:00",
    "@context": "http://vocab.odpt.org/context_odpt.jsonld",
    "dct:issued": "2023-03-18",
    "owl:sameAs": "odpt.RailwayFare:Tokyu.Ikegami.Yukigayaotsuka.Tokyu.TokyuShinYokohama.ShinTsunashima",
    "odpt:operator": "odpt.Operator:Tokyu",
    "odpt:toStation": "odpt.Station:Tokyu.TokyuShinYokohama.ShinTsunashima",
    "odpt:icCardFare": 250,
    "odpt:ticketFare": 250,
    "odpt:fromStation": "odpt.Station:Tokyu.Ikegami.Yukigayaotsuka",
    "odpt:childIcCardFare": 125,
    "odpt:childTicketFare": 130
  },
  {
    "@id": "urn:ucode:_00001C000000000000010000039A37BC",
    "@type": "odpt:RailwayFare",
    "dc:date": "2025-06-30T15:00:00+09:00",
    "@context": "http://vocab.odpt.org/context_odpt.jsonld",
    "dct:issued": "2023-03-18",
    "owl:sameAs": "odpt.RailwayFare:Tokyu.Ikegami.Yukigayaotsuka.Tokyu.TokyuShinYokohama.ShinYokohama",
    "odpt:operator": "odpt.Operator:Tokyu",
    "odpt:toStation": "odpt.Station:Tokyu.TokyuShinYokohama.ShinYokohama",
    "odpt:icCardFare": 358,
    "odpt:ticketFare": 360,
    "odpt:fromStation": "odpt.Station:Tokyu.Ikegami.Yukigayaotsuka",
    "odpt:childIcCardFare": 179,
    "odpt:childTicketFare": 180
  },
  {
    "@id": "urn:ucode:_00001C0000000000000100000317A5D6",
    "@type": "odpt:RailwayFare",
    "dc:date": "2025-06-30T15:00:00+09:00",
    "@context": "http://vocab.odpt.org/context_odpt.jsonld",
    "dct:issued": "2023-03-18",
    "owl:sameAs": "odpt.RailwayFare:Tokyu.Ikegami.Yukigayaotsuka.Tokyu.TokyuTamagawa.Kamata",
    "odpt:operator": "odpt.Operator:Tokyu",
    "odpt:toStation": "odpt.Station:Tokyu.TokyuTamagawa.Kamata",
    "odpt:icCardFare": 180,
    "odpt:ticketFare": 180,
    "odpt:fromStation": "odpt.Station:Tokyu.Ikegami.Yukigayaotsuka",
    "odpt:childIcCardFare": 90,
    "odpt:childTicketFare": 90
  },
  {
    "@id": "urn:ucode:_00001C0000000000000100000317A5D7",
    "@type": "odpt:RailwayFare",
    "dc:date": "2025-06-30T15:00:00+09:00",
    "@context": "http://vocab.odpt.org/context_odpt.jsonld",
    "dct:issued": "2023-03-18",
    "owl:sameAs": "odpt.RailwayFare:Tokyu.Ikegami.Yukigayaotsuka.Tokyu.TokyuTamagawa.MusashiNitta",
    "odpt:operator": "odpt.Operator:Tokyu",
    "odpt:toStation": "odpt.Station:Tokyu.TokyuTamagawa.MusashiNitta",
    "odpt:icCardFare": 227,
    "odpt:ticketFare": 230,
    "odpt:fromStation": "odpt.Station:Tokyu.Ikegami.Yukigayaotsuka",
    "odpt:childIcCardFare": 113,
    "odpt:childTicketFare": 120
  },
  {
    "@id": "urn:ucode:_00001C0000000000000100000317A5D8",
    "@type": "odpt:RailwayFare",
    "dc:date": "2025-06-30T15:00:00+09:00",
    "@context": "http://vocab.odpt.org/context_odpt.jsonld",
    "dct:issued": "2023-03-18",
    "owl:sameAs": "odpt.RailwayFare:Tokyu.Ikegami.Yukigayaotsuka.Tokyu.TokyuTamagawa.Numabe",
    "odpt:operator": "odpt.Operator:Tokyu",
    "odpt:toStation": "odpt.Station:Tokyu.TokyuTamagawa.Numabe",
    "odpt:icCardFare": 227,
    "odpt:ticketFare": 230,
    "odpt:fromStation": "odpt.Station:Tokyu.Ikegami.Yukigayaotsuka",
    "odpt:childIcCardFare": 113,
    "odpt:childTicketFare": 120
  },
  {
    "@id": "urn:ucode:_00001C0000000000000100000317A5D9",
    "@type": "odpt:RailwayFare",
    "dc:date": "2025-06-30T15:00:00+09:00",
    "@context": "http://vocab.odpt.org/context_odpt.jsonld",
    "dct:issued": "2023-03-18",
    "owl:sameAs": "odpt.RailwayFare:Tokyu.Ikegami.Yukigayaotsuka.Tokyu.TokyuTamagawa.Shimomaruko",
    "odpt:operator": "odpt.Operator:Tokyu",
    "odpt:toStation": "odpt.Station:Tokyu.TokyuTamagawa.Shimomaruko",
    "odpt:icCardFare": 227,
    "odpt:ticketFare": 230,
    "odpt:fromStation": "odpt.Station:Tokyu.Ikegami.Yukigayaotsuka",
    "odpt:childIcCardFare": 113,
    "odpt:childTicketFare": 120
  },
  {
    "@id": "urn:ucode:_00001C0000000000000100000317A5DA",
    "@type": "odpt:RailwayFare",
    "dc:date": "2025-06-30T15:00:00+09:00",
    "@context": "http://vocab.odpt.org/context_odpt.jsonld",
    "dct:issued": "2023-03-18",
    "owl:sameAs": "odpt.RailwayFare:Tokyu.Ikegami.Yukigayaotsuka.Tokyu.TokyuTamagawa.Tamagawa",
    "odpt:operator": "odpt.Operator:Tokyu",
    "odpt:toStation": "odpt.Station:Tokyu.TokyuTamagawa.Tamagawa",
    "odpt:icCardFare": 227,
    "odpt:ticketFare": 230,
    "odpt:fromStation": "odpt.Station:Tokyu.Ikegami.Yukigayaotsuka",
    "odpt:childIcCardFare": 113,
    "odpt:childTicketFare": 120
  },
  {
    "@id": "urn:ucode:_00001C0000000000000100000317A5DB",
    "@type": "odpt:RailwayFare",
    "dc:date": "2025-06-30T15:00:00+09:00",
    "@context": "http://vocab.odpt.org/context_odpt.jsonld",
    "dct:issued": "2023-03-18",
    "owl:sameAs": "odpt.RailwayFare:Tokyu.Ikegami.Yukigayaotsuka.Tokyu.TokyuTamagawa.Unoki",
    "odpt:operator": "odpt.Operator:Tokyu",
    "odpt:toStation": "odpt.Station:Tokyu.TokyuTamagawa.Unoki",
    "odpt:icCardFare": 227,
    "odpt:ticketFare": 230,
    "odpt:fromStation": "odpt.Station:Tokyu.Ikegami.Yukigayaotsuka",
    "odpt:childIcCardFare": 113,
    "odpt:childTicketFare": 120
  },
  {
    "@id": "urn:ucode:_00001C0000000000000100000317A5DC",
    "@type": "odpt:RailwayFare",
    "dc:date": "2025-06-30T15:00:00+09:00",
    "@context": "http://vocab.odpt.org/context_odpt.jsonld",
    "dct:issued": "2023-03-18",
    "owl:sameAs": "odpt.RailwayFare:Tokyu.Ikegami.Yukigayaotsuka.Tokyu.TokyuTamagawa.YaguchiNoWatashi",
    "odpt:operator": "odpt.Operator:Tokyu",
    "odpt:toStation": "odpt.Station:Tokyu.TokyuTamagawa.YaguchiNoWatashi",
    "odpt:icCardFare": 180,
    "odpt:ticketFare": 180,
    "odpt:fromStation": "odpt.Station:Tokyu.Ikegami.Yukigayaotsuka",
    "odpt:childIcCardFare": 90,
    "odpt:childTicketFare": 90
  },
  {
    "@id": "urn:ucode:_00001C0000000000000100000317A5DD",
    "@type": "odpt:RailwayFare",
    "dc:date": "2025-06-30T15:00:00+09:00",
    "@context": "http://vocab.odpt.org/context_odpt.jsonld",
    "dct:issued": "2023-03-18",
    "owl:sameAs": "odpt.RailwayFare:Tokyu.Ikegami.Yukigayaotsuka.Tokyu.Toyoko.DaikanYama",
    "odpt:operator": "odpt.Operator:Tokyu",
    "odpt:toStation": "odpt.Station:Tokyu.Toyoko.DaikanYama",
    "odpt:icCardFare": 250,
    "odpt:ticketFare": 250,
    "odpt:fromStation": "odpt.Station:Tokyu.Ikegami.Yukigayaotsuka",
    "odpt:childIcCardFare": 125,
    "odpt:childTicketFare": 130
  },
  {
    "@id": "urn:ucode:_00001C0000000000000100000317A5DE",
    "@type": "odpt:RailwayFare",
    "dc:date": "2025-06-30T15:00:00+09:00",
    "@context": "http://vocab.odpt.org/context_odpt.jsonld",
    "dct:issued": "2023-03-18",
    "owl:sameAs": "odpt.RailwayFare:Tokyu.Ikegami.Yukigayaotsuka.Tokyu.Toyoko.DenEnChofu",
    "odpt:operator": "odpt.Operator:Tokyu",
    "odpt:toStation": "odpt.Station:Tokyu.Toyoko.DenEnChofu",
    "odpt:icCardFare": 180,
    "odpt:ticketFare": 180,
    "odpt:fromStation": "odpt.Station:Tokyu.Ikegami.Yukigayaotsuka",
    "odpt:childIcCardFare": 90,
    "odpt:childTicketFare": 90
  },
  {
    "@id": "urn:ucode:_00001C0000000000000100000317A5DF",
    "@type": "odpt:RailwayFare",
    "dc:date": "2025-06-30T15:00:00+09:00",
    "@context": "http://vocab.odpt.org/context_odpt.jsonld",
    "dct:issued": "2023-03-18",
    "owl:sameAs": "odpt.RailwayFare:Tokyu.Ikegami.Yukigayaotsuka.Tokyu.Toyoko.GakugeiDaigaku",
    "odpt:operator": "odpt.Operator:Tokyu",
    "odpt:toStation": "odpt.Station:Tokyu.Toyoko.GakugeiDaigaku",
    "odpt:icCardFare": 227,
    "odpt:ticketFare": 230,
    "odpt:fromStation": "odpt.Station:Tokyu.Ikegami.Yukigayaotsuka",
    "odpt:childIcCardFare": 113,
    "odpt:childTicketFare": 120
  },
  {
    "@id": "urn:ucode:_00001C0000000000000100000317A5E0",
    "@type": "odpt:RailwayFare",
    "dc:date": "2025-06-30T15:00:00+09:00",
    "@context": "http://vocab.odpt.org/context_odpt.jsonld",
    "dct:issued": "2023-03-18",
    "owl:sameAs": "odpt.RailwayFare:Tokyu.Ikegami.Yukigayaotsuka.Tokyu.Toyoko.Hakuraku",
    "odpt:operator": "odpt.Operator:Tokyu",
    "odpt:toStation": "odpt.Station:Tokyu.Toyoko.Hakuraku",
    "odpt:icCardFare": 288,
    "odpt:ticketFare": 290,
    "odpt:fromStation": "odpt.Station:Tokyu.Ikegami.Yukigayaotsuka",
    "odpt:childIcCardFare": 144,
    "odpt:childTicketFare": 150
  },
  {
    "@id": "urn:ucode:_00001C0000000000000100000317A5E1",
    "@type": "odpt:RailwayFare",
    "dc:date": "2025-06-30T15:00:00+09:00",
    "@context": "http://vocab.odpt.org/context_odpt.jsonld",
    "dct:issued": "2023-03-18",
    "owl:sameAs": "odpt.RailwayFare:Tokyu.Ikegami.Yukigayaotsuka.Tokyu.Toyoko.HigashiHakuraku",
    "odpt:operator": "odpt.Operator:Tokyu",
    "odpt:toStation": "odpt.Station:Tokyu.Toyoko.HigashiHakuraku",
    "odpt:icCardFare": 309,
    "odpt:ticketFare": 310,
    "odpt:fromStation": "odpt.Station:Tokyu.Ikegami.Yukigayaotsuka",
    "odpt:childIcCardFare": 154,
    "odpt:childTicketFare": 160
  },
  {
    "@id": "urn:ucode:_00001C0000000000000100000317A5E2",
    "@type": "odpt:RailwayFare",
    "dc:date": "2025-06-30T15:00:00+09:00",
    "@context": "http://vocab.odpt.org/context_odpt.jsonld",
    "dct:issued": "2023-03-18",
    "owl:sameAs": "odpt.RailwayFare:Tokyu.Ikegami.Yukigayaotsuka.Tokyu.Toyoko.Hiyoshi",
    "odpt:operator": "odpt.Operator:Tokyu",
    "odpt:toStation": "odpt.Station:Tokyu.Toyoko.Hiyoshi",
    "odpt:icCardFare": 250,
    "odpt:ticketFare": 250,
    "odpt:fromStation": "odpt.Station:Tokyu.Ikegami.Yukigayaotsuka",
    "odpt:childIcCardFare": 125,
    "odpt:childTicketFare": 130
  },
  {
    "@id": "urn:ucode:_00001C0000000000000100000317A5E3",
    "@type": "odpt:RailwayFare",
    "dc:date": "2025-06-30T15:00:00+09:00",
    "@context": "http://vocab.odpt.org/context_odpt.jsonld",
    "dct:issued": "2023-03-18",
    "owl:sameAs": "odpt.RailwayFare:Tokyu.Ikegami.Yukigayaotsuka.Tokyu.Toyoko.Jiyugaoka",
    "odpt:operator": "odpt.Operator:Tokyu",
    "odpt:toStation": "odpt.Station:Tokyu.Toyoko.Jiyugaoka",
    "odpt:icCardFare": 180,
    "odpt:ticketFare": 180,
    "odpt:fromStation": "odpt.Station:Tokyu.Ikegami.Yukigayaotsuka",
    "odpt:childIcCardFare": 90,
    "odpt:childTicketFare": 90
  },
  {
    "@id": "urn:ucode:_00001C0000000000000100000317A5E4",
    "@type": "odpt:RailwayFare",
    "dc:date": "2025-06-30T15:00:00+09:00",
    "@context": "http://vocab.odpt.org/context_odpt.jsonld",
    "dct:issued": "2023-03-18",
    "owl:sameAs": "odpt.RailwayFare:Tokyu.Ikegami.Yukigayaotsuka.Tokyu.Toyoko.Kikuna",
    "odpt:operator": "odpt.Operator:Tokyu",
    "odpt:toStation": "odpt.Station:Tokyu.Toyoko.Kikuna",
    "odpt:icCardFare": 288,
    "odpt:ticketFare": 290,
    "odpt:fromStation": "odpt.Station:Tokyu.Ikegami.Yukigayaotsuka",
    "odpt:childIcCardFare": 144,
    "odpt:childTicketFare": 150
  },
  {
    "@id": "urn:ucode:_00001C0000000000000100000317A5E5",
    "@type": "odpt:RailwayFare",
    "dc:date": "2025-06-30T15:00:00+09:00",
    "@context": "http://vocab.odpt.org/context_odpt.jsonld",
    "dct:issued": "2023-03-18",
    "owl:sameAs": "odpt.RailwayFare:Tokyu.Ikegami.Yukigayaotsuka.Tokyu.Toyoko.Motosumiyoshi",
    "odpt:operator": "odpt.Operator:Tokyu",
    "odpt:toStation": "odpt.Station:Tokyu.Toyoko.Motosumiyoshi",
    "odpt:icCardFare": 227,
    "odpt:ticketFare": 230,
    "odpt:fromStation": "odpt.Station:Tokyu.Ikegami.Yukigayaotsuka",
    "odpt:childIcCardFare": 113,
    "odpt:childTicketFare": 120
  },
  {
    "@id": "urn:ucode:_00001C0000000000000100000317A5E6",
    "@type": "odpt:RailwayFare",
    "dc:date": "2025-06-30T15:00:00+09:00",
    "@context": "http://vocab.odpt.org/context_odpt.jsonld",
    "dct:issued": "2023-03-18",
    "owl:sameAs": "odpt.RailwayFare:Tokyu.Ikegami.Yukigayaotsuka.Tokyu.Toyoko.MusashiKosugi",
    "odpt:operator": "odpt.Operator:Tokyu",
    "odpt:toStation": "odpt.Station:Tokyu.Toyoko.MusashiKosugi",
    "odpt:icCardFare": 227,
    "odpt:ticketFare": 230,
    "odpt:fromStation": "odpt.Station:Tokyu.Ikegami.Yukigayaotsuka",
    "odpt:childIcCardFare": 113,
    "odpt:childTicketFare": 120
  },
  {
    "@id": "urn:ucode:_00001C0000000000000100000317A5E7",
    "@type": "odpt:RailwayFare",
    "dc:date": "2025-06-30T15:00:00+09:00",
    "@context": "http://vocab.odpt.org/context_odpt.jsonld",
    "dct:issued": "2023-03-18",
    "owl:sameAs": "odpt.RailwayFare:Tokyu.Ikegami.Yukigayaotsuka.Tokyu.Toyoko.Myorenji",
    "odpt:operator": "odpt.Operator:Tokyu",
    "odpt:toStation": "odpt.Station:Tokyu.Toyoko.Myorenji",
    "odpt:icCardFare": 288,
    "odpt:ticketFare": 290,
    "odpt:fromStation": "odpt.Station:Tokyu.Ikegami.Yukigayaotsuka",
    "odpt:childIcCardFare": 144,
    "odpt:childTicketFare": 150
  },
  {
    "@id": "urn:ucode:_00001C0000000000000100000317A5E8",
    "@type": "odpt:RailwayFare",
    "dc:date": "2025-06-30T15:00:00+09:00",
    "@context": "http://vocab.odpt.org/context_odpt.jsonld",
    "dct:issued": "2023-03-18",
    "owl:sameAs": "odpt.RailwayFare:Tokyu.Ikegami.Yukigayaotsuka.Tokyu.Toyoko.NakaMeguro",
    "odpt:operator": "odpt.Operator:Tokyu",
    "odpt:toStation": "odpt.Station:Tokyu.Toyoko.NakaMeguro",
    "odpt:icCardFare": 227,
    "odpt:ticketFare": 230,
    "odpt:fromStation": "odpt.Station:Tokyu.Ikegami.Yukigayaotsuka",
    "odpt:childIcCardFare": 113,
    "odpt:childTicketFare": 120
  },
  {
    "@id": "urn:ucode:_00001C0000000000000100000317A5E9",
    "@type": "odpt:RailwayFare",
    "dc:date": "2025-06-30T15:00:00+09:00",
    "@context": "http://vocab.odpt.org/context_odpt.jsonld",
    "dct:issued": "2023-03-18",
    "owl:sameAs": "odpt.RailwayFare:Tokyu.Ikegami.Yukigayaotsuka.Tokyu.Toyoko.Okurayama",
    "odpt:operator": "odpt.Operator:Tokyu",
    "odpt:toStation": "odpt.Station:Tokyu.Toyoko.Okurayama",
    "odpt:icCardFare": 288,
    "odpt:ticketFare": 290,
    "odpt:fromStation": "odpt.Station:Tokyu.Ikegami.Yukigayaotsuka",
    "odpt:childIcCardFare": 144,
    "odpt:childTicketFare": 150
  },
  {
    "@id": "urn:ucode:_00001C0000000000000100000317A5EA",
    "@type": "odpt:RailwayFare",
    "dc:date": "2025-06-30T15:00:00+09:00",
    "@context": "http://vocab.odpt.org/context_odpt.jsonld",
    "dct:issued": "2023-03-18",
    "owl:sameAs": "odpt.RailwayFare:Tokyu.Ikegami.Yukigayaotsuka.Tokyu.Toyoko.Shibuya",
    "odpt:operator": "odpt.Operator:Tokyu",
    "odpt:toStation": "odpt.Station:Tokyu.Toyoko.Shibuya",
    "odpt:icCardFare": 250,
    "odpt:ticketFare": 250,
    "odpt:fromStation": "odpt.Station:Tokyu.Ikegami.Yukigayaotsuka",
    "odpt:childIcCardFare": 125,
    "odpt:childTicketFare": 130
  },
  {
    "@id": "urn:ucode:_00001C0000000000000100000317A5EB",
    "@type": "odpt:RailwayFare",
    "dc:date": "2025-06-30T15:00:00+09:00",
    "@context": "http://vocab.odpt.org/context_odpt.jsonld",
    "dct:issued": "2023-03-18",
    "owl:sameAs": "odpt.RailwayFare:Tokyu.Ikegami.Yukigayaotsuka.Tokyu.Toyoko.ShinMaruko",
    "odpt:operator": "odpt.Operator:Tokyu",
    "odpt:toStation": "odpt.Station:Tokyu.Toyoko.ShinMaruko",
    "odpt:icCardFare": 227,
    "odpt:ticketFare": 230,
    "odpt:fromStation": "odpt.Station:Tokyu.Ikegami.Yukigayaotsuka",
    "odpt:childIcCardFare": 113,
    "odpt:childTicketFare": 120
  },
  {
    "@id": "urn:ucode:_00001C0000000000000100000317A5EC",
    "@type": "odpt:RailwayFare",
    "dc:date": "2025-06-30T15:00:00+09:00",
    "@context": "http://vocab.odpt.org/context_odpt.jsonld",
    "dct:issued": "2023-03-18",
    "owl:sameAs": "odpt.RailwayFare:Tokyu.Ikegami.Yukigayaotsuka.Tokyu.Toyoko.Tamagawa",
    "odpt:operator": "odpt.Operator:Tokyu",
    "odpt:toStation": "odpt.Station:Tokyu.Toyoko.Tamagawa",
    "odpt:icCardFare": 227,
    "odpt:ticketFare": 230,
    "odpt:fromStation": "odpt.Station:Tokyu.Ikegami.Yukigayaotsuka",
    "odpt:childIcCardFare": 113,
    "odpt:childTicketFare": 120
  },
  {
    "@id": "urn:ucode:_00001C0000000000000100000317A5ED",
    "@type": "odpt:RailwayFare",
    "dc:date": "2025-06-30T15:00:00+09:00",
    "@context": "http://vocab.odpt.org/context_odpt.jsonld",
    "dct:issued": "2023-03-18",
    "owl:sameAs": "odpt.RailwayFare:Tokyu.Ikegami.Yukigayaotsuka.Tokyu.Toyoko.Tammachi",
    "odpt:operator": "odpt.Operator:Tokyu",
    "odpt:toStation": "odpt.Station:Tokyu.Toyoko.Tammachi",
    "odpt:icCardFare": 309,
    "odpt:ticketFare": 310,
    "odpt:fromStation": "odpt.Station:Tokyu.Ikegami.Yukigayaotsuka",
    "odpt:childIcCardFare": 154,
    "odpt:childTicketFare": 160
  },
  {
    "@id": "urn:ucode:_00001C0000000000000100000317A5EE",
    "@type": "odpt:RailwayFare",
    "dc:date": "2025-06-30T15:00:00+09:00",
    "@context": "http://vocab.odpt.org/context_odpt.jsonld",
    "dct:issued": "2023-03-18",
    "owl:sameAs": "odpt.RailwayFare:Tokyu.Ikegami.Yukigayaotsuka.Tokyu.Toyoko.ToritsuDaigaku",
    "odpt:operator": "odpt.Operator:Tokyu",
    "odpt:toStation": "odpt.Station:Tokyu.Toyoko.ToritsuDaigaku",
    "odpt:icCardFare": 180,
    "odpt:ticketFare": 180,
    "odpt:fromStation": "odpt.Station:Tokyu.Ikegami.Yukigayaotsuka",
    "odpt:childIcCardFare": 90,
    "odpt:childTicketFare": 90
  },
  {
    "@id": "urn:ucode:_00001C0000000000000100000317A5EF",
    "@type": "odpt:RailwayFare",
    "dc:date": "2025-06-30T15:00:00+09:00",
    "@context": "http://vocab.odpt.org/context_odpt.jsonld",
    "dct:issued": "2023-03-18",
    "owl:sameAs": "odpt.RailwayFare:Tokyu.Ikegami.Yukigayaotsuka.Tokyu.Toyoko.Tsunashima",
    "odpt:operator": "odpt.Operator:Tokyu",
    "odpt:toStation": "odpt.Station:Tokyu.Toyoko.Tsunashima",
    "odpt:icCardFare": 250,
    "odpt:ticketFare": 250,
    "odpt:fromStation": "odpt.Station:Tokyu.Ikegami.Yukigayaotsuka",
    "odpt:childIcCardFare": 125,
    "odpt:childTicketFare": 130
  },
  {
    "@id": "urn:ucode:_00001C0000000000000100000317A5F0",
    "@type": "odpt:RailwayFare",
    "dc:date": "2025-06-30T15:00:00+09:00",
    "@context": "http://vocab.odpt.org/context_odpt.jsonld",
    "dct:issued": "2023-03-18",
    "owl:sameAs": "odpt.RailwayFare:Tokyu.Ikegami.Yukigayaotsuka.Tokyu.Toyoko.Yokohama",
    "odpt:operator": "odpt.Operator:Tokyu",
    "odpt:toStation": "odpt.Station:Tokyu.Toyoko.Yokohama",
    "odpt:icCardFare": 309,
    "odpt:ticketFare": 310,
    "odpt:fromStation": "odpt.Station:Tokyu.Ikegami.Yukigayaotsuka",
    "odpt:childIcCardFare": 154,
    "odpt:childTicketFare": 160
  },
  {
    "@id": "urn:ucode:_00001C0000000000000100000317A5F1",
    "@type": "odpt:RailwayFare",
    "dc:date": "2025-06-30T15:00:00+09:00",
    "@context": "http://vocab.odpt.org/context_odpt.jsonld",
    "dct:issued": "2023-03-18",
    "owl:sameAs": "odpt.RailwayFare:Tokyu.Ikegami.Yukigayaotsuka.Tokyu.Toyoko.Yutenji",
    "odpt:operator": "odpt.Operator:Tokyu",
    "odpt:toStation": "odpt.Station:Tokyu.Toyoko.Yutenji",
    "odpt:icCardFare": 227,
    "odpt:ticketFare": 230,
    "odpt:fromStation": "odpt.Station:Tokyu.Ikegami.Yukigayaotsuka",
    "odpt:childIcCardFare": 113,
    "odpt:childTicketFare": 120
  }
]
